{"stats":{"minecraft:used":{"minecraft:birch_fence":64,"minecraft:stone_bricks":13,"minecraft:oak_log":1,"minecraft:glass":1,"minecraft:black_concrete":2,"minecraft:polished_deepslate_slab":14,"minecraft:glowstone":50,"minecraft:brown_carpet":2,"minecraft:white_carpet":16,"minecraft:red_wool":8,"minecraft:light_blue_wool":43,"minecraft:spruce_stairs":7,"minecraft:brown_wool":4,"minecraft:oak_planks":189,"minecraft:green_wool":11,"minecraft:light_gray_carpet":1,"minecraft:polished_diorite_stairs":20,"minecraft:white_terracotta":9},"minecraft:picked_up":{"minecraft:white_carpet":34,"minecraft:gray_carpet":5,"minecraft:light_gray_carpet":10},"minecraft:dropped":{"minecraft:wooden_axe":1},"minecraft:custom":{"minecraft:time_since_rest":76769,"minecraft:crouch_one_cm":151,"minecraft:sprint_one_cm":5086,"minecraft:play_time":76769,"minecraft:walk_one_cm":54452,"minecraft:sneak_time":4263,"minecraft:drop":1,"minecraft:jump":137,"minecraft:leave_game":12,"minecraft:time_since_death":76769,"minecraft:total_world_time":90953,"minecraft:fly_one_cm":1635406}},"DataVersion":3465}