{"timestamp": 1731561501257,"timestamp_f":"Today, 05:18","last_7_days":{"new_players":0,"downtime":0,"new_players_retention":0,"average_tps":"20","unique_players_day":1,"unique_players":1,"low_tps_spikes":0,"new_players_retention_perc":"-"},"weeks":{"unique_after":1,"sessions_after":8,"new_trend":{"text":"0","reversed":false},"average_playtime_before":7545564,"regular_before":3,"deaths_trend":{"text":"0","reversed":true},"unique_trend":{"text":"0","reversed":false},"mob_kills_trend":{"text":"0","reversed":false},"regular_trend":{"text":"2","direction":"-","reversed":false},"player_kills_before":0,"midpoint":1730956701256,"end":1731561501256,"new_before":0,"new_after":0,"unique_before":1,"deaths_after":0,"player_kills_trend":{"text":"0","reversed":false},"average_playtime_after":14379389,"regular_after":1,"start":1730351901256,"deaths_before":0,"sessions_trend":{"text":"2","direction":"+","reversed":false},"player_kills_after":0,"average_playtime_trend":{"text":"6833825","direction":"+","reversed":false},"mob_kills_before":0,"sessions_before":6,"mob_kills_after":0},"numbers":{"sessions":662,"regular_players":1,"best_peak_players":"3","total_players":9,"playtime":974146802,"last_peak_date":1731418625013,"online_players":0,"mob_kills":3,"player_playtime":108238533,"current_uptime":1873351616,"last_peak_players":"1","best_peak_date":1722438008308,"player_kills":0,"deaths":1}}